Metadata-Version: 1.0
Name: pygogogate2
Version: 0.0.5
Summary: Python package for controlling Gogogate2-Enabled Garage Door
Home-page: https://github.com/dlbroadfoot/pygogogate2
Author: David Broadfoot
Author-email: dbroadfoot@gmail.com
License: MIT License
